{
  "theme": "professional",
  "meta": {
    "title": "项目调研报告（卡片结构示例）",
    "author": "epic-doc Demo"
  },
  "header": { "text": "项目调研报告（示例）", "align": "right" },
  "footer": { "text": "epic-doc", "page_number": true, "align": "center" },
  "blocks": [
    { "type": "heading", "text": "奥托精密零部件（苏州）有限公司", "level": 1 },
    { "type": "paragraph", "text": "项目编号：MES-2022-SZ-017 · 2022年3月—2022年11月", "align": "left" },
    { "type": "callout", "style": "success", "title": "状态", "text": "已上线" },

    {
      "type": "table",
      "headers": false,
      "style": "grid",
      "col_widths": [1.3, 2.6, 1.3, 2.0],
      "data": [
        ["行业", "汽车零部件", "客户规模", "2个工厂 / 1200人"],
        ["实施工期", "8个月", "合同金额", "380万元"]
      ],
      "caption": "概览信息（卡片式 2×2 网格）"
    },

    { "type": "heading", "text": "核心需求模块（模拟 Tab 区）", "level": 2 },
    {
      "type": "paragraph",
      "text": "工单管理  |  生产计划排程  |  质量管理（SPC）  |  追溯管理  |  设备管理  |  报表中心",
      "align": "left"
    },
    { "type": "hr" },

    { "type": "heading", "text": "客户核心痛点（调研原始结论）", "level": 2 },
    {
      "type": "table",
      "headers": true,
      "style": "striped",
      "col_widths": [1.2, 4.8],
      "data": [
        ["等级", "描述"],
        ["最痛点", "生产过程全靠纸质工单，发现质量问题无法追溯到具体操作人员和批次原材料"],
        ["次痛点", "计划排程依赖 Excel，插单频繁导致产能数据混乱，无法准确承诺交期"],
        ["隐性需求", "客户总部（德国）要求在 2023 年前通过 IATF 16949 复审，追溯能力是审核重点"]
      ]
    },

    { "type": "heading", "text": "集成与技术约束", "level": 2 },
    {
      "type": "table",
      "headers": true,
      "style": "grid",
      "col_widths": [1.5, 4.5],
      "data": [
        ["条目", "内容"],
        ["已有系统", "SAP ECC 6.0（生产订单下发）；自研 WMS（仓库）"],
        ["集成方向", "SAP → MES（工单）；MES → SAP（报工/良品数量）；MES → WMS（物料消耗）"],
        ["设备协议", "三菱 PLC，支持 OPC-UA；老设备 20 台需加装采集网关"]
      ]
    },

    { "type": "heading", "text": "项目亮点（可复用经验）", "level": 2 },
    {
      "type": "callout",
      "style": "success",
      "title": "追溯方案",
      "text": "采用“批次码 + 条码枪扫描”替代 RFID，成本降低约 60%，客户接受度高。建议在其他有 IATF 追溯需求的客户优先推广此方案。"
    },
    {
      "type": "callout",
      "style": "info",
      "title": "SPC 模块",
      "text": "上线前先做 2 周数据收集期，用历史数据给客户演示控制图，显著提升对该模块价值的认同度。"
    },

    { "type": "heading", "text": "项目风险与教训", "level": 2 },
    {
      "type": "callout",
      "style": "warning",
      "title": "SAP 接口评估",
      "text": "SAP 接口联调低估工期约 2 倍：原以为走标准 BAPI，实际为高度定制化版本，需要重写 RFC 接口。后续项目建议在合同前置接口评估。"
    },
    {
      "type": "callout",
      "style": "danger",
      "title": "需求变更",
      "text": "客户 IT 部门在项目中途更换负责人，导致服务路径与计划重新规划，延期约 3 周。建议在合同中增加“环境变更的工期保护条款”。"
    },

    { "type": "heading", "text": "适用搜索标签", "level": 2 },
    {
      "type": "paragraph",
      "text": "#汽车零部件  #IATF追溯  #SPC质量  #SAP集成  #OPC-UA  #SAP定制化风险  #条码追溯方案  #中型工厂",
      "align": "left"
    }
  ]
}

